{"graph": {"_type": "graph-file", "sha256": "afb6ae3ecc489c2831a14c091f87343590ed6901f26a324049c4194c2b166055", "size": 2726, "path": "media/graph/graph_summary_afb6ae3ecc489c2831a1.graph.json"}, "validation_sample_0": {"_type": "images/separated", "width": 180, "height": 180, "format": "png", "count": 1, "filenames": ["media/images/validation_sample_0_0_b7beeaa1ae2a18145894.png"], "captions": ["True: Uninfected, Pred: Prasitized"]}, "_timestamp": 1718803787.3480203, "_runtime": 37.51357936859131, "_step": 9, "validation_sample_1": {"_type": "images/separated", "width": 180, "height": 180, "format": "png", "count": 1, "filenames": ["media/images/validation_sample_1_1_b33cd115eef51a8c08df.png"], "captions": ["True: Uninfected, Pred: Prasitized"]}, "validation_sample_2": {"_type": "images/separated", "width": 180, "height": 180, "format": "png", "count": 1, "filenames": ["media/images/validation_sample_2_2_40900cbd300956b756ec.png"], "captions": ["True: Prasitized, Pred: Prasitized"]}, "validation_sample_3": {"_type": "images/separated", "width": 180, "height": 180, "format": "png", "count": 1, "filenames": ["media/images/validation_sample_3_3_a29a3042260aefe3d31d.png"], "captions": ["True: Uninfected, Pred: Prasitized"]}, "validation_sample_4": {"_type": "images/separated", "width": 180, "height": 180, "format": "png", "count": 1, "filenames": ["media/images/validation_sample_4_4_e91064e25dd4d7e75280.png"], "captions": ["True: Prasitized, Pred: Prasitized"]}, "validation_sample_5": {"_type": "images/separated", "width": 180, "height": 180, "format": "png", "count": 1, "filenames": ["media/images/validation_sample_5_5_856057c4390270a4fc7c.png"], "captions": ["True: Uninfected, Pred: Prasitized"]}, "validation_sample_6": {"_type": "images/separated", "width": 180, "height": 180, "format": "png", "count": 1, "filenames": ["media/images/validation_sample_6_6_0d54791e2b27e6a0ce1e.png"], "captions": ["True: Prasitized, Pred: Prasitized"]}, "validation_sample_7": {"_type": "images/separated", "width": 180, "height": 180, "format": "png", "count": 1, "filenames": ["media/images/validation_sample_7_7_80921ae11010839aaafc.png"], "captions": ["True: Uninfected, Pred: Prasitized"]}, "validation_sample_8": {"_type": "images/separated", "width": 180, "height": 180, "format": "png", "count": 1, "filenames": ["media/images/validation_sample_8_8_373c9f72bd79e327e395.png"], "captions": ["True: Uninfected, Pred: Prasitized"]}, "validation_sample_9": {"_type": "images/separated", "width": 180, "height": 180, "format": "png", "count": 1, "filenames": ["media/images/validation_sample_9_9_1eb069c28cff86e00a66.png"], "captions": ["True: Uninfected, Pred: Prasitized"]}, "_wandb": {"runtime": 63}}